alertemail/__init__.py
alertemail/alertemail.py
potatoscript/__init__.py
potatoscript/alertemail.py
potatoscript/emailalert.py
sck/__init__.py
sck/emailalert.py
emailalert-1.4.7.dist-info/METADATA
emailalert-1.4.7.dist-info/WHEEL
emailalert-1.4.7.dist-info/top_level.txt
emailalert-1.4.7.dist-info/RECORD
