Metadata-Version: 2.1
Name: emailalert
Version: 1.4.7
Summary: A simple library for sending alert email with attachmment
Author: ks lim
Author-email: kianseng.lim@sony.com
